ourgptmodel/__init__.py
ourgptmodel/app.py
ourgptmodel/gpt.py
ourgptmodel/modelfile
ourgptmodel/requirements.txt
ourgptmodel-0.1.0.dist-info/METADATA
ourgptmodel-0.1.0.dist-info/WHEEL
ourgptmodel-0.1.0.dist-info/RECORD
