Metadata-Version: 2.1
Name: ourgptmodel
Version: 0.1.0
Summary: 
Author: Your Name
Author-email: you@example.com
Requires-Python: >=3.12,<4.0
Classifier: Programming Language :: Python :: 3
Classifier: Programming Language :: Python :: 3.12
Requires-Dist: gradio (>=4.23.0,<5.0.0)
Requires-Dist: langchain (>=0.1.13,<0.2.0)
